01_UpDown_Counter/counter.v
module up_down_counter (
    input clk,
    input reset,
    input up_down,
    output reg [3:0] count
);

    always @(posedge clk or posedge reset) begin
        if (reset) begin
            count <= 4'b0000;
        end else if (up_down) begin
            count <= count + 1'b1;
        end else begin
            count <= count - 1'b1;
        end
    end

endmodule

01_UpDown_Counter/tb_counter.v
module tb_counter;
    reg clk;
    reg reset;
    reg up_down;
    wire [3:0] count;

    up_down_counter uut (.clk(clk), .reset(reset), .up_down(up_down), .count(count));

    always #5 clk = ~clk;

    initial begin
        clk = 0; reset = 1; up_down = 1;
        #10 reset = 0;
        #50 up_down = 0;
        #50 reset = 1;
        #10 reset = 0;
        #20 $finish;
    end

    initial begin
        $dumpfile("counter.vcd");
        $dumpvars(0, tb_counter);
    end
endmodule

01_UpDown_Counter/counter.vcd
$date
	Mon Aug 10 19:27:43 2026
$end
$version
	Icarus Verilog
$end
$timescale
	1s
$end
$scope module tb_counter $end
$var wire 4 ! count [3:0] $end
$var reg 1 " clk $end
$var reg 1 # reset $end
$var reg 1 $ up_down $end
$scope module uut $end
$var wire 1 " clk $end
$var wire 1 # reset $end
$var wire 1 $ up_down $end
$var reg 4 % count [3:0] $end
$upscope $end
$upscope $end
$enddefinitions $end
$comment Show the parameter values. $end
$dumpall
$end
#0
$dumpvars
b0 %
1$
1#
0"
b0 !
$end
#5
1"
#10
0"
0#
#15
b1 !
b1 %
1"
#20
0"
#25
b10 !
b10 %
1"
#30
0"
#35
b11 !
b11 %
1"
#40
0"
#45
b100 !
b100 %
1"
#50
0"
#55
b101 !
b101 %
1"
#60
0"
0$
#65
b100 !
b100 %
1"
#70
0"
#75
b11 !
b11 %
1"
#80
0"
#85
b10 !
b10 %
1"
#90
0"
#95
b1 !
b1 %
1"
#100
0"
#105
b0 !
b0 %
1"
#110
0"
1#
#115
1"
#120
0"
0#
#125
b1111 !
b1111 %
1"
#130
0"
#135
b1110 !
b1110 %
1"
