02_Traffic_Light_FSM/traffic_fsm.v
module traffic_fsm (
    input clk,
    input reset,
    input vehicle_detected,   // Side street sensor
    input crosswalk_request,  // Pedestrian button
    input emergency_override, // Ambulance/Fire override
    
    output reg [2:0] main_light, // {Red, Yellow, Green}
    output reg [2:0] side_light,
    output reg walk_signal       // 1 = Walk, 0 = Don't Walk
);

    // State Encodings (Binary)
    localparam MAIN_GREEN   = 3'b000;
    localparam MAIN_YELLOW  = 3'b001;
    localparam SIDE_GREEN   = 3'b010;
    localparam SIDE_YELLOW  = 3'b011;
    localparam CROSSWALK    = 3'b100;
    localparam EMERGENCY    = 3'b101;

    reg [2:0] current_state, next_state;

    // Block 1: State Register (Sequential - updates on clock edge)
    always @(posedge clk or posedge reset) begin
        if (reset)
            current_state <= MAIN_GREEN;
        else
            current_state <= next_state;
    end

    // Block 2: Next State Logic (Combinational - decides where to go next)
    always @(*) begin
        // Default assignment to prevent latches
        next_state = current_state;

        if (emergency_override) begin
            next_state = EMERGENCY;
        end else begin
            case (current_state)
                MAIN_GREEN: begin
                    if (crosswalk_request) next_state = MAIN_YELLOW;
                    else if (vehicle_detected) next_state = MAIN_YELLOW;
                end
                MAIN_YELLOW: begin
                    if (crosswalk_request) next_state = CROSSWALK;
                    else next_state = SIDE_GREEN;
                end
                SIDE_GREEN: begin
                    if (!vehicle_detected || crosswalk_request) next_state = SIDE_YELLOW;
                end
                SIDE_YELLOW: begin
                    next_state = MAIN_GREEN;
                end
                CROSSWALK: begin
                    next_state = MAIN_GREEN;
                end
                EMERGENCY: begin
                    if (!emergency_override) next_state = MAIN_GREEN;
                end
                default: next_state = MAIN_GREEN;
            endcase
        end
    end

    // Block 3: Output Logic (Combinational - drives the actual lights)
    always @(*) begin
        // Default all to Red/Stop to prevent latches and accidents
        main_light = 3'b100; 
        side_light = 3'b100; 
        walk_signal = 1'b0;

        case (current_state)
            MAIN_GREEN:  begin main_light = 3'b001; end // Main Green
            MAIN_YELLOW: begin main_light = 3'b010; end // Main Yellow
            SIDE_GREEN:  begin side_light = 3'b001; end // Side Green
            SIDE_YELLOW: begin side_light = 3'b010; end // Side Yellow
            CROSSWALK:   begin walk_signal = 1'b1;  end // Pedestrian Walk
            EMERGENCY:   begin 
                main_light = 3'b100; // Force Red
                side_light = 3'b100; // Force Red
            end
        endcase
    end
endmodule

02_Traffic_Light_FSM/tb_traffic_fsm.v
module tb_traffic_fsm;
    reg clk, reset, vehicle_detected, crosswalk_request, emergency_override;
    wire [2:0] main_light, side_light;
    wire walk_signal;

    traffic_fsm uut (
        .clk(clk), .reset(reset), .vehicle_detected(vehicle_detected),
        .crosswalk_request(crosswalk_request), .emergency_override(emergency_override),
        .main_light(main_light), .side_light(side_light), .walk_signal(walk_signal)
    );

    always #5 clk = ~clk;

    initial begin
        $dumpfile("traffic_fsm.vcd");
        $dumpvars(0, tb_traffic_fsm);

        // Initialize
        clk = 0; reset = 1; vehicle_detected = 0; crosswalk_request = 0; emergency_override = 0;
        #10 reset = 0;

        // Test 1: Normal operation, car arrives on side street
        #20 vehicle_detected = 1;
        #40 vehicle_detected = 0;

        // Test 2: Pedestrian wants to cross
        #20 crosswalk_request = 1;
        #10 crosswalk_request = 0;

        // Test 3: Ambulance override
        #40 emergency_override = 1;
        #30 emergency_override = 0;

        #50 $finish;
    end
endmodule

02_Traffic_Light_FSM/traffic_fsm.vcd
$date
	Wed Aug 12 08:02:09 2026
$end
$version
	Icarus Verilog
$end
$timescale
	1s
$end
$scope module tb_traffic_fsm $end
$var wire 1 ! walk_signal $end
$var wire 3 " side_light [2:0] $end
$var wire 3 # main_light [2:0] $end
$var reg 1 $ clk $end
$var reg 1 % crosswalk_request $end
$var reg 1 & emergency_override $end
$var reg 1 ' reset $end
$var reg 1 ( vehicle_detected $end
$scope module uut $end
$var wire 1 $ clk $end
$var wire 1 % crosswalk_request $end
$var wire 1 & emergency_override $end
$var wire 1 ' reset $end
$var wire 1 ( vehicle_detected $end
$var parameter 3 ) CROSSWALK $end
$var parameter 3 * EMERGENCY $end
$var parameter 3 + MAIN_GREEN $end
$var parameter 3 , MAIN_YELLOW $end
$var parameter 3 - SIDE_GREEN $end
$var parameter 3 . SIDE_YELLOW $end
$var reg 3 / current_state [2:0] $end
$var reg 3 0 main_light [2:0] $end
$var reg 3 1 next_state [2:0] $end
$var reg 3 2 side_light [2:0] $end
$var reg 1 ! walk_signal $end
$upscope $end
$upscope $end
$enddefinitions $end
$comment Show the parameter values. $end
$dumpall
b11 .
b10 -
b1 ,
b0 +
b101 *
b100 )
$end
#0
$dumpvars
b100 2
b0 1
b1 0
b0 /
0(
1'
0&
0%
0$
b1 #
b100 "
0!
$end
#5
1$
#10
0$
0'
#15
1$
#20
0$
#25
1$
#30
b1 1
0$
1(
#35
b10 #
b10 0
b10 1
b1 /
1$
#40
0$
#45
b1 "
b1 2
b100 #
b100 0
b10 /
1$
#50
0$
#55
1$
#60
0$
#65
1$
#70
b11 1
0$
0(
#75
b10 "
b10 2
b0 1
b11 /
1$
#80
0$
#85
b1 #
b1 0
b100 "
b100 2
b0 /
1$
#90
b1 1
0$
1%
#95
b10 #
b10 0
b100 1
b1 /
1$
#100
b10 1
0$
0%
#105
b1 "
b1 2
b100 #
b100 0
b11 1
b10 /
1$
#110
0$
#115
b10 "
b10 2
b0 1
b11 /
1$
#120
0$
#125
b1 #
b1 0
b100 "
b100 2
b0 /
1$
#130
0$
#135
1$
#140
b101 1
0$
1&
#145
b100 #
b100 0
b101 /
1$
#150
0$
#155
1$
#160
0$
#165
1$
#170
b0 1
0$
0&
#175
b1 #
b1 0
b0 /
1$
